pioneer/das/view/QtWrappers.py
pioneer/das/view/__init__.py
pioneer/das/view/metadata.yml
pioneer/das/view/viewer.py
pioneer/das/view/apps/__init__.py
pioneer/das/view/apps/check_synchronization.py
pioneer/das/view/apps/dasview.py
pioneer/das/view/qml/root_CameraCalibration.qml
pioneer/das/view/qml/root_calib_editor.qml
pioneer/das/view/qml/root_das.qml
pioneer/das/view/qml/root_minimal_live_example.qml
pioneer/das/view/qml/root_pixell_demo.qml
pioneer/das/view/qml/Das/AnnotationTab.qml
pioneer/das/view/qml/Das/CalibrationEditor.qml
pioneer/das/view/qml/Das/CalibrationICP.qml
pioneer/das/view/qml/Das/DatasourceWindow.qml
pioneer/das/view/qml/Das/LidarActor.qml
pioneer/das/view/qml/Das/MetadataEditor.qml
pioneer/das/view/qml/Das/PCLUI2D.qml
pioneer/das/view/qml/Das/Player.qml
pioneer/das/view/qml/Das/RGBDatasourceWindow.qml
pioneer/das/view/qml/Das/ScalarsWindow.qml
pioneer/das/view/qml/Das/TracesWindow.qml
pioneer/das/view/qml/Das/ViewportWindow.qml
pioneer/das/view/qml/Das/qmldir
pioneer/das/view/windows/__init__.py
pioneer/das/view/windows/calib_window.py
pioneer/das/view/windows/imager_window.py
pioneer/das/view/windows/metadata_window.py
pioneer/das/view/windows/player_window.py
pioneer/das/view/windows/scalars_window.py
pioneer/das/view/windows/traces_window.py
pioneer/das/view/windows/viewport_window.py
pioneer/das/view/windows/window.py
pioneer_das_view-1.4.1.dist-info/DESCRIPTION.rst
pioneer_das_view-1.4.1.dist-info/METADATA
pioneer_das_view-1.4.1.dist-info/RECORD
pioneer_das_view-1.4.1.dist-info/WHEEL
pioneer_das_view-1.4.1.dist-info/dependency_links.txt
pioneer_das_view-1.4.1.dist-info/entry_points.txt
pioneer_das_view-1.4.1.dist-info/metadata.json
pioneer_das_view-1.4.1.dist-info/top_level.txt
