Metadata-Version: 2.0
Name: pioneer-das-view
Version: 1.4.1
Summary: Leddartech's das view
Home-page: UNKNOWN
Author: Leddartech
License: UNKNOWN
Platform: UNKNOWN
Classifier: Programming Language :: Python :: 3
Classifier: License :: OSI Approved :: MIT License
Classifier: Operating System :: OS Independent
Requires-Python: >=3.6
Requires-Dist: PyQt5 (==5.14)
Requires-Dist: docopt
Requires-Dist: matplotlib
Requires-Dist: numpy
Requires-Dist: opencv-python
Requires-Dist: pandas
Requires-Dist: pioneer-common-gui (>=1.4.0)
Requires-Dist: pioneer-common (>=1.2.0)
Requires-Dist: pioneer-das-api (>=1.4.0)
Requires-Dist: pyyaml
Requires-Dist: tqdm
Requires-Dist: utm
